discord/__init__.py
discord/backoff.py
discord/base.py
discord/client.py
discord/context.py
discord/enums.py
discord/exceptions.py
discord/state.py
discord/api/__init__.py
discord/api/cache.py
discord/api/dispatch.py
discord/api/enums.py
discord/api/error.py
discord/api/errors.py
discord/api/exceptions.py
discord/api/gateway.py
discord/api/http.py
discord/api/utils.py
discord/api/models/__init__.py
discord/api/models/channel.py
discord/api/models/gift.py
discord/api/models/guild.py
discord/api/models/integration.py
discord/api/models/intents.py
discord/api/models/member.py
discord/api/models/message.py
discord/api/models/misc.py
discord/api/models/presence.py
discord/api/models/role.py
discord/api/models/team.py
discord/api/models/user.py
discord/api/models/voice.py
discord/ext/__init__.py
discord/ext/const.py
discord/ext/tasks/__init__.py
discord/models/__init__.py
discord/models/activity.py
discord/models/asset.py
discord/models/colour.py
discord/models/command.py
discord/models/component.py
discord/models/embeds.py
discord/models/emoji.py
discord/models/enums.py
discord/models/flags.py
discord/models/guild.py
discord/models/member.py
discord/models/misc.py
discord/models/object.py
discord/models/partial_emoji.py
discord/models/permissions.py
discord/models/role.py
discord/models/user.py
discord/models/utils.py
discord_continued-1.0.8.dist-info/LICENSE
discord_continued-1.0.8.dist-info/METADATA
discord_continued-1.0.8.dist-info/WHEEL
discord_continued-1.0.8.dist-info/top_level.txt
discord_continued-1.0.8.dist-info/RECORD
